ultimate_trading_solution/__init__.py
ultimate_trading_solution/api/__init__.py
ultimate_trading_solution/api/main.py
ultimate_trading_solution/cli.py
ultimate_trading_solution/core/__init__.py
ultimate_trading_solution/core/config.py
ultimate_trading_solution/core/database.py
ultimate_trading_solution/core/logger.py
ultimate_trading_solution-0.1.0.dist-info/LICENSE
ultimate_trading_solution-0.1.0.dist-info/METADATA
ultimate_trading_solution-0.1.0.dist-info/WHEEL
ultimate_trading_solution-0.1.0.dist-info/entry_points.txt
ultimate_trading_solution-0.1.0.dist-info/RECORD
