Metadata-Version: 2.3
Name: ultimate-trading-solution
Version: 0.1.0
Summary: A comprehensive trading solution with advanced analytics and automation
License: MIT
Keywords: trading,finance,analytics,automation
Author: Your Name
Author-email: your.email@example.com
Requires-Python: >=3.11,<4.0
Classifier: Development Status :: 3 - Alpha
Classifier: Intended Audience :: Financial and Insurance Industry
Classifier: License :: OSI Approved :: MIT License
Classifier: Programming Language :: Python :: 3
Classifier: Programming Language :: Python :: 3.11
Classifier: Programming Language :: Python :: 3.12
Classifier: Programming Language :: Python :: 3.13
Classifier: Topic :: Office/Business :: Financial :: Investment
Requires-Dist: aiofiles (>=23.0.0,<24.0.0)
Requires-Dist: alembic (>=1.11.0,<2.0.0)
Requires-Dist: celery (>=5.3.0,<6.0.0)
Requires-Dist: click (>=8.1.0,<9.0.0)
Requires-Dist: fastapi (>=0.100.0,<0.101.0)
Requires-Dist: httpx (>=0.24.0,<0.25.0)
Requires-Dist: numpy (>=1.24.0,<2.0.0)
Requires-Dist: pandas (>=2.0.0,<3.0.0)
Requires-Dist: pydantic (>=2.0.0,<3.0.0)
Requires-Dist: python-dotenv (>=1.0.0,<2.0.0)
Requires-Dist: redis (>=4.6.0,<5.0.0)
Requires-Dist: requests (>=2.31.0,<3.0.0)
Requires-Dist: rich (>=13.0.0,<14.0.0)
Requires-Dist: sqlalchemy (>=2.0.0,<3.0.0)
Requires-Dist: structlog (>=23.0.0,<24.0.0)
Requires-Dist: uvicorn[standard] (>=0.23.0,<0.24.0)
Project-URL: Documentation, https://yourusername.github.io/ultimate-trading-solution
Project-URL: Homepage, https://github.com/yourusername/ultimate-trading-solution
Project-URL: Repository, https://github.com/yourusername/ultimate-trading-solution.git
